pycaptions/__init__.py
pycaptions/captions.py
pycaptions/cli.py
pycaptions/microTime.py
pycaptions/styling.py
pycaptions/development/__init__.py
pycaptions/development/block.py
pycaptions/development/blockType.py
pycaptions/development/captionsFormat.py
pycaptions/development/colors.py
pycaptions/development/styleFormat.py
pycaptions/development/text.py
pycaptions/development/wrappers.py
pycaptions/lrc/__init__.py
pycaptions/lrc/_class.py
pycaptions/lrc/functions.py
pycaptions/options/__init__.py
pycaptions/options/fileExtension.py
pycaptions/options/style.py
pycaptions/sami/__init__.py
pycaptions/sami/_class.py
pycaptions/sami/functions.py
pycaptions/srt/__init__.py
pycaptions/srt/_class.py
pycaptions/srt/functions.py
pycaptions/srt/style.py
pycaptions/sub/__init__.py
pycaptions/sub/_class.py
pycaptions/sub/functions.py
pycaptions/sub/style.py
pycaptions/ttml/__init__.py
pycaptions/ttml/_class.py
pycaptions/ttml/extras.py
pycaptions/ttml/functions.py
pycaptions/ttml/style.py
pycaptions/usf/__init__.py
pycaptions/usf/_class.py
pycaptions/usf/functions.py
pycaptions/vtt/__init__.py
pycaptions/vtt/_class.py
pycaptions/vtt/functions.py
pycaptions/vtt/style.py
test/__init__.py
test/test_captions.py
pycaptions-0.7.0.dist-info/LICENCE
pycaptions-0.7.0.dist-info/METADATA
pycaptions-0.7.0.dist-info/WHEEL
pycaptions-0.7.0.dist-info/entry_points.txt
pycaptions-0.7.0.dist-info/top_level.txt
pycaptions-0.7.0.dist-info/RECORD
