Metadata-Version: 2.1
Name: pycaptions
Version: 0.7.0
Summary: PyCaptions, parser and converter for captions formats
Home-page: https://github.com/adfreelife/PyCaptions
Author: Ad Free Life
Keywords: captions,subtitles
Classifier: Development Status :: 4 - Beta
Classifier: Programming Language :: Python :: 3 :: Only
Classifier: License :: OSI Approved :: GNU Lesser General Public License v3 (LGPLv3)
Classifier: Operating System :: OS Independent
License-File: LICENCE
Requires-Dist: beautifulsoup4
Requires-Dist: cssutils
Requires-Dist: budoux >=0.6.2
Requires-Dist: langcodes >=3.2.0
Requires-Dist: charset-normalizer >=3.0.0
Requires-Dist: webcolors
Requires-Dist: lxml
